odoo/addons/la_feixa/__init__.py
odoo/addons/la_feixa/__manifest__.py
odoo/addons/la_feixa/controllers/__init__.py
odoo/addons/la_feixa/controllers/website_subscription.py
odoo/addons/la_feixa/models/__init__.py
odoo/addons/la_feixa/models/company.py
odoo/addons/la_feixa/models/subscription_request.py
odoo/addons/la_feixa/views/become_cooperator_view.xml
odoo/addons/la_feixa/views/cooperator_thanks_view.xml
odoo/addons/la_feixa/views/res_company_view.xml
odoo/addons/la_feixa/views/subscription_request_view.xml
odoo12_addon_la_feixa-12.0.0.0.38.dist-info/METADATA
odoo12_addon_la_feixa-12.0.0.0.38.dist-info/WHEEL
odoo12_addon_la_feixa-12.0.0.0.38.dist-info/top_level.txt
odoo12_addon_la_feixa-12.0.0.0.38.dist-info/RECORD
