Metadata-Version: 2.1
Name: odoo12-addon-la_feixa
Version: 12.0.0.0.38
Summary: Odoo La Feixa customizations
Home-page: https://coopdevs.org
Author: Coopdevs Treball SCCL
License: AGPL-3
Classifier: Programming Language :: Python
Classifier: Framework :: Odoo
Classifier: Framework :: Odoo :: 12.0
Classifier: License :: OSI Approved :: GNU Affero General Public License v3
Requires-Python: >=3.5
Requires-Dist: odoo12-addon-easy-my-coop-es
Requires-Dist: odoo12-addon-purchase-products-only-from-vendors
Requires-Dist: odoo<12.1dev,>=12.0a
